{
    "centers": [
      {
        "center_id": 572168,
        "name": "Yatdam PHC",
        "address": "Yatdam",
        "state_name": "Arunachal Pradesh",
        "district_name": "Changlang",
        "block_name": "Changlang",
        "pincode": 792120,
        "lat": 27,
        "long": 96,
        "from": "09:00:00",
        "to": "17:00:00",
        "fee_type": "Free",
        "sessions": [
          {
            "session_id": "b48208f8-45b5-4ffe-b3ba-dcb11b2ac6d4",
            "date": "26-05-2021",
            "available_capacity": 0,
            "min_age_limit": 45,
            "vaccine": "COVISHIELD",
            "slots": [
              "09:00AM-11:00AM",
              "11:00AM-01:00PM",
              "01:00PM-03:00PM",
              "03:00PM-05:00PM"
            ],
            "available_capacity_dose1": 0,
            "available_capacity_dose2": 0
          },
          {
            "session_id": "58177763-8190-4809-a9c0-2573ac2eaafe",
            "date": "27-05-2021",
            "available_capacity": 0,
            "min_age_limit": 45,
            "vaccine": "COVISHIELD",
            "slots": [
              "09:00AM-11:00AM",
              "11:00AM-01:00PM",
              "01:00PM-03:00PM",
              "03:00PM-05:00PM"
            ],
            "available_capacity_dose1": 0,
            "available_capacity_dose2": 0
          },
          {
            "session_id": "8c57343d-dd17-4955-9cd0-f18eeac85fe8",
            "date": "28-05-2021",
            "available_capacity": 0,
            "min_age_limit": 45,
            "vaccine": "COVISHIELD",
            "slots": [
              "09:00AM-11:00AM",
              "11:00AM-01:00PM",
              "01:00PM-03:00PM",
              "03:00PM-05:00PM"
            ],
            "available_capacity_dose1": 0,
            "available_capacity_dose2": 0
          },
          {
            "session_id": "38cd8ae7-3be4-454f-8093-64d27ba71ac1",
            "date": "29-05-2021",
            "available_capacity": 0,
            "min_age_limit": 45,
            "vaccine": "COVISHIELD",
            "slots": [
              "09:00AM-11:00AM",
              "11:00AM-01:00PM",
              "01:00PM-03:00PM",
              "03:00PM-05:00PM"
            ],
            "available_capacity_dose1": 0,
            "available_capacity_dose2": 0
          },
          {
            "session_id": "805b9b22-0c23-47a0-bdc2-a2c1f3dd721d",
            "date": "30-05-2021",
            "available_capacity": 0,
            "min_age_limit": 45,
            "vaccine": "COVISHIELD",
            "slots": [
              "09:00AM-11:00AM",
              "11:00AM-01:00PM",
              "01:00PM-03:00PM",
              "03:00PM-05:00PM"
            ],
            "available_capacity_dose1": 0,
            "available_capacity_dose2": 0
          },
          {
            "session_id": "6b66f4c8-19ab-4702-b8f5-27cc6390ad41",
            "date": "31-05-2021",
            "available_capacity": 0,
            "min_age_limit": 45,
            "vaccine": "COVISHIELD",
            "slots": [
              "09:00AM-11:00AM",
              "11:00AM-01:00PM",
              "01:00PM-03:00PM",
              "03:00PM-05:00PM"
            ],
            "available_capacity_dose1": 0,
            "available_capacity_dose2": 0
          }
        ]
      },
      {
        "center_id": 85257,
        "name": "Namtok PHC",
        "address": "Namtok",
        "state_name": "Arunachal Pradesh",
        "district_name": "Changlang",
        "block_name": "Changlang",
        "pincode": 792120,
        "lat": 27,
        "long": 96,
        "from": "09:00:00",
        "to": "17:00:00",
        "fee_type": "Free",
        "sessions": [
          {
            "session_id": "056614ce-dd47-4b94-b114-6caf627a595f",
            "date": "26-05-2021",
            "available_capacity": 0,
            "min_age_limit": 45,
            "vaccine": "COVISHIELD",
            "slots": [
              "09:00AM-11:00AM",
              "11:00AM-01:00PM",
              "01:00PM-03:00PM",
              "03:00PM-05:00PM"
            ],
            "available_capacity_dose1": 0,
            "available_capacity_dose2": 0
          },
          {
            "session_id": "8e74b1c0-95b8-49ca-93d4-8006e9825729",
            "date": "27-05-2021",
            "available_capacity": 0,
            "min_age_limit": 45,
            "vaccine": "COVISHIELD",
            "slots": [
              "09:00AM-11:00AM",
              "11:00AM-01:00PM",
              "01:00PM-03:00PM",
              "03:00PM-05:00PM"
            ],
            "available_capacity_dose1": 0,
            "available_capacity_dose2": 0
          },
          {
            "session_id": "4aaf9e42-ed2f-4ce5-95d2-bc3abc51b0eb",
            "date": "28-05-2021",
            "available_capacity": 0,
            "min_age_limit": 45,
            "vaccine": "COVISHIELD",
            "slots": [
              "09:00AM-11:00AM",
              "11:00AM-01:00PM",
              "01:00PM-03:00PM",
              "03:00PM-05:00PM"
            ],
            "available_capacity_dose1": 0,
            "available_capacity_dose2": 0
          },
          {
            "session_id": "83639fbe-468f-4ca7-a22d-7e85cad48a78",
            "date": "29-05-2021",
            "available_capacity": 0,
            "min_age_limit": 45,
            "vaccine": "COVISHIELD",
            "slots": [
              "09:00AM-11:00AM",
              "11:00AM-01:00PM",
              "01:00PM-03:00PM",
              "03:00PM-05:00PM"
            ],
            "available_capacity_dose1": 0,
            "available_capacity_dose2": 0
          },
          {
            "session_id": "caed4947-9911-4732-8c42-1a06b46fb9f4",
            "date": "30-05-2021",
            "available_capacity": 0,
            "min_age_limit": 45,
            "vaccine": "COVISHIELD",
            "slots": [
              "09:00AM-11:00AM",
              "11:00AM-01:00PM",
              "01:00PM-03:00PM",
              "03:00PM-05:00PM"
            ],
            "available_capacity_dose1": 0,
            "available_capacity_dose2": 0
          },
          {
            "session_id": "399ab29d-fac7-4ae1-a544-64b27ed01d09",
            "date": "31-05-2021",
            "available_capacity": 0,
            "min_age_limit": 45,
            "vaccine": "COVISHIELD",
            "slots": [
              "09:00AM-11:00AM",
              "11:00AM-01:00PM",
              "01:00PM-03:00PM",
              "03:00PM-05:00PM"
            ],
            "available_capacity_dose1": 0,
            "available_capacity_dose2": 0
          }
        ]
      },
      {
        "center_id": 85259,
        "name": "DH Changlang",
        "address": "DH Changlang",
        "state_name": "Arunachal Pradesh",
        "district_name": "Changlang",
        "block_name": "Changlang",
        "pincode": 792120,
        "lat": 27,
        "long": 95,
        "from": "09:00:00",
        "to": "17:00:00",
        "fee_type": "Free",
        "sessions": [
          {
            "session_id": "20373407-d06d-4194-8db7-d05978a4d870",
            "date": "26-05-2021",
            "available_capacity": 38,
            "min_age_limit": 45,
            "vaccine": "COVISHIELD",
            "slots": [
              "09:00AM-11:00AM",
              "11:00AM-01:00PM",
              "01:00PM-03:00PM",
              "03:00PM-05:00PM"
            ],
            "available_capacity_dose1": 18,
            "available_capacity_dose2": 20
          },
          {
            "session_id": "f78294aa-466d-4a69-8487-7a6e8ffeeb2e",
            "date": "26-05-2021",
            "available_capacity": 0,
            "min_age_limit": 18,
            "vaccine": "COVISHIELD",
            "slots": [
              "09:00AM-11:00AM",
              "11:00AM-01:00PM",
              "01:00PM-03:00PM",
              "03:00PM-05:00PM"
            ],
            "available_capacity_dose1": 0,
            "available_capacity_dose2": 0
          },
          {
            "session_id": "50aaff36-addc-4bcb-9249-a77e70305a8e",
            "date": "27-05-2021",
            "available_capacity": 37,
            "min_age_limit": 45,
            "vaccine": "COVISHIELD",
            "slots": [
              "09:00AM-11:00AM",
              "11:00AM-01:00PM",
              "01:00PM-03:00PM",
              "03:00PM-05:00PM"
            ],
            "available_capacity_dose1": 17,
            "available_capacity_dose2": 20
          },
          {
            "session_id": "1ebb8d09-018a-4f7b-8ac2-1268a3ccddeb",
            "date": "28-05-2021",
            "available_capacity": 20,
            "min_age_limit": 45,
            "vaccine": "COVISHIELD",
            "slots": [
              "09:00AM-11:00AM",
              "11:00AM-01:00PM",
              "01:00PM-03:00PM",
              "03:00PM-05:00PM"
            ],
            "available_capacity_dose1": 10,
            "available_capacity_dose2": 10
          },
          {
            "session_id": "ad48f8cc-79bc-4c7f-bf65-acd18a1887d2",
            "date": "29-05-2021",
            "available_capacity": 39,
            "min_age_limit": 45,
            "vaccine": "COVISHIELD",
            "slots": [
              "09:00AM-11:00AM",
              "11:00AM-01:00PM",
              "01:00PM-03:00PM",
              "03:00PM-05:00PM"
            ],
            "available_capacity_dose1": 19,
            "available_capacity_dose2": 20
          },
          {
            "session_id": "1aa4cf7a-3cb1-4781-a7c6-bae67eeaf839",
            "date": "30-05-2021",
            "available_capacity": 40,
            "min_age_limit": 45,
            "vaccine": "COVISHIELD",
            "slots": [
              "09:00AM-11:00AM",
              "11:00AM-01:00PM",
              "01:00PM-03:00PM",
              "03:00PM-05:00PM"
            ],
            "available_capacity_dose1": 20,
            "available_capacity_dose2": 20
          },
          {
            "session_id": "7d2fd8c8-cb17-4a73-8054-26e171843220",
            "date": "31-05-2021",
            "available_capacity": 20,
            "min_age_limit": 45,
            "vaccine": "COVISHIELD",
            "slots": [
              "09:00AM-11:00AM",
              "11:00AM-01:00PM",
              "01:00PM-03:00PM",
              "03:00PM-05:00PM"
            ],
            "available_capacity_dose1": 10,
            "available_capacity_dose2": 10
          }
        ]
      },
      {
        "center_id": 597460,
        "name": "CHC Manmao",
        "address": "Manmao",
        "state_name": "Arunachal Pradesh",
        "district_name": "Changlang",
        "block_name": "Jairampur",
        "pincode": 792121,
        "lat": 27,
        "long": 95,
        "from": "09:00:00",
        "to": "17:00:00",
        "fee_type": "Free",
        "sessions": [
          {
            "session_id": "17e9ede9-e8ea-4d26-bec9-6bff55dcccd3",
            "date": "26-05-2021",
            "available_capacity": 0,
            "min_age_limit": 45,
            "vaccine": "COVISHIELD",
            "slots": [
              "09:00AM-11:00AM",
              "11:00AM-01:00PM",
              "01:00PM-03:00PM",
              "03:00PM-05:00PM"
            ],
            "available_capacity_dose1": 0,
            "available_capacity_dose2": 0
          },
          {
            "session_id": "ed0136d5-8717-4a30-b54e-e73a4513f518",
            "date": "27-05-2021",
            "available_capacity": 0,
            "min_age_limit": 45,
            "vaccine": "COVISHIELD",
            "slots": [
              "09:00AM-11:00AM",
              "11:00AM-01:00PM",
              "01:00PM-03:00PM",
              "03:00PM-05:00PM"
            ],
            "available_capacity_dose1": 0,
            "available_capacity_dose2": 0
          },
          {
            "session_id": "cbbb0f5f-36f0-4910-9e56-578f58a94af2",
            "date": "28-05-2021",
            "available_capacity": 0,
            "min_age_limit": 45,
            "vaccine": "COVISHIELD",
            "slots": [
              "09:00AM-11:00AM",
              "11:00AM-01:00PM",
              "01:00PM-03:00PM",
              "03:00PM-05:00PM"
            ],
            "available_capacity_dose1": 0,
            "available_capacity_dose2": 0
          },
          {
            "session_id": "06710e66-0167-4853-9749-4d95de3efe25",
            "date": "29-05-2021",
            "available_capacity": 0,
            "min_age_limit": 45,
            "vaccine": "COVISHIELD",
            "slots": [
              "09:00AM-11:00AM",
              "11:00AM-01:00PM",
              "01:00PM-03:00PM",
              "03:00PM-06:00PM"
            ],
            "available_capacity_dose1": 0,
            "available_capacity_dose2": 0
          },
          {
            "session_id": "e517eb33-fafe-4271-9f73-3e63f211669b",
            "date": "30-05-2021",
            "available_capacity": 0,
            "min_age_limit": 45,
            "vaccine": "COVISHIELD",
            "slots": [
              "09:00AM-11:00AM",
              "11:00AM-01:00PM",
              "01:00PM-03:00PM",
              "03:00PM-05:00PM"
            ],
            "available_capacity_dose1": 0,
            "available_capacity_dose2": 0
          },
          {
            "session_id": "1113a9ad-7de2-492e-b37f-86ca49ddcfcb",
            "date": "31-05-2021",
            "available_capacity": 0,
            "min_age_limit": 45,
            "vaccine": "COVISHIELD",
            "slots": [
              "09:00AM-11:00AM",
              "11:00AM-01:00PM",
              "01:00PM-03:00PM",
              "03:00PM-05:00PM"
            ],
            "available_capacity_dose1": 0,
            "available_capacity_dose2": 0
          }
        ]
      },
      {
        "center_id": 566927,
        "name": "Miao CHC",
        "address": "Miao Town",
        "state_name": "Arunachal Pradesh",
        "district_name": "Changlang",
        "block_name": "Khagam Miao",
        "pincode": 792122,
        "lat": 27,
        "long": 96,
        "from": "09:00:00",
        "to": "17:00:00",
        "fee_type": "Free",
        "sessions": [
          {
            "session_id": "73f99972-97b1-41a3-9702-9ae250c69f43",
            "date": "26-05-2021",
            "available_capacity": 0,
            "min_age_limit": 18,
            "vaccine": "COVISHIELD",
            "slots": [
              "09:00AM-11:00AM",
              "11:00AM-01:00PM",
              "01:00PM-03:00PM",
              "03:00PM-05:00PM"
            ],
            "available_capacity_dose1": 0,
            "available_capacity_dose2": 0
          },
          {
            "session_id": "a0c726ab-d3d4-4dc7-9424-f8962372e653",
            "date": "26-05-2021",
            "available_capacity": 35,
            "min_age_limit": 45,
            "vaccine": "COVISHIELD",
            "slots": [
              "09:00AM-11:00AM",
              "11:00AM-01:00PM",
              "01:00PM-03:00PM",
              "03:00PM-05:00PM"
            ],
            "available_capacity_dose1": 15,
            "available_capacity_dose2": 20
          },
          {
            "session_id": "f3987302-dfab-4942-a74b-b0a7c16618f4",
            "date": "27-05-2021",
            "available_capacity": 40,
            "min_age_limit": 45,
            "vaccine": "COVISHIELD",
            "slots": [
              "09:00AM-11:00AM",
              "11:00AM-01:00PM",
              "01:00PM-03:00PM",
              "03:00PM-05:00PM"
            ],
            "available_capacity_dose1": 20,
            "available_capacity_dose2": 20
          },
          {
            "session_id": "fbf6e2ee-7baf-441d-a348-09238e36b2f0",
            "date": "28-05-2021",
            "available_capacity": 40,
            "min_age_limit": 45,
            "vaccine": "COVISHIELD",
            "slots": [
              "09:00AM-11:00AM",
              "11:00AM-01:00PM",
              "01:00PM-03:00PM",
              "03:00PM-05:00PM"
            ],
            "available_capacity_dose1": 20,
            "available_capacity_dose2": 20
          },
          {
            "session_id": "e861cd60-a523-4dbb-9d11-af40ad0e7339",
            "date": "29-05-2021",
            "available_capacity": 40,
            "min_age_limit": 45,
            "vaccine": "COVISHIELD",
            "slots": [
              "09:00AM-11:00AM",
              "11:00AM-01:00PM",
              "01:00PM-03:00PM",
              "03:00PM-06:00PM"
            ],
            "available_capacity_dose1": 20,
            "available_capacity_dose2": 20
          },
          {
            "session_id": "584d2074-c3a2-4a8e-8d21-2e6fcf46f56a",
            "date": "30-05-2021",
            "available_capacity": 40,
            "min_age_limit": 45,
            "vaccine": "COVISHIELD",
            "slots": [
              "09:00AM-11:00AM",
              "11:00AM-01:00PM",
              "01:00PM-03:00PM",
              "03:00PM-05:00PM"
            ],
            "available_capacity_dose1": 20,
            "available_capacity_dose2": 20
          },
          {
            "session_id": "77b0fcc2-3482-48f7-8c1c-e3a51780e63f",
            "date": "31-05-2021",
            "available_capacity": 40,
            "min_age_limit": 45,
            "vaccine": "COVISHIELD",
            "slots": [
              "09:00AM-11:00AM",
              "11:00AM-01:00PM",
              "01:00PM-03:00PM",
              "03:00PM-05:00PM"
            ],
            "available_capacity_dose1": 20,
            "available_capacity_dose2": 20
          }
        ]
      },
      {
        "center_id": 570521,
        "name": "Nampong PHC",
        "address": "Nampong",
        "state_name": "Arunachal Pradesh",
        "district_name": "Changlang",
        "block_name": "Nampong",
        "pincode": 792123,
        "lat": 27,
        "long": 96,
        "from": "09:00:00",
        "to": "17:00:00",
        "fee_type": "Free",
        "sessions": [
          {
            "session_id": "c974dad3-bdc6-4fa8-846c-fd12b201372b",
            "date": "26-05-2021",
            "available_capacity": 20,
            "min_age_limit": 45,
            "vaccine": "COVISHIELD",
            "slots": [
              "09:00AM-11:00AM",
              "11:00AM-01:00PM",
              "01:00PM-03:00PM",
              "03:00PM-05:00PM"
            ],
            "available_capacity_dose1": 10,
            "available_capacity_dose2": 10
          },
          {
            "session_id": "b62c2dd2-3da3-4f2f-97b4-33377d58d88e",
            "date": "27-05-2021",
            "available_capacity": 20,
            "min_age_limit": 45,
            "vaccine": "COVISHIELD",
            "slots": [
              "09:00AM-11:00AM",
              "11:00AM-01:00PM",
              "01:00PM-03:00PM",
              "03:00PM-05:00PM"
            ],
            "available_capacity_dose1": 10,
            "available_capacity_dose2": 10
          },
          {
            "session_id": "1a480f52-fb4d-42e1-8b96-b58f7aaf57d4",
            "date": "28-05-2021",
            "available_capacity": 20,
            "min_age_limit": 45,
            "vaccine": "COVISHIELD",
            "slots": [
              "09:00AM-11:00AM",
              "11:00AM-01:00PM",
              "01:00PM-03:00PM",
              "03:00PM-05:00PM"
            ],
            "available_capacity_dose1": 10,
            "available_capacity_dose2": 10
          },
          {
            "session_id": "6bf8f25c-feb1-4831-9d88-c86729a6e636",
            "date": "29-05-2021",
            "available_capacity": 20,
            "min_age_limit": 45,
            "vaccine": "COVISHIELD",
            "slots": [
              "09:00AM-11:00AM",
              "11:00AM-01:00PM",
              "01:00PM-03:00PM",
              "03:00PM-05:00PM"
            ],
            "available_capacity_dose1": 10,
            "available_capacity_dose2": 10
          },
          {
            "session_id": "406a85b4-76d4-4737-a919-acc868f56346",
            "date": "30-05-2021",
            "available_capacity": 20,
            "min_age_limit": 45,
            "vaccine": "COVISHIELD",
            "slots": [
              "09:00AM-11:00AM",
              "11:00AM-01:00PM",
              "01:00PM-03:00PM",
              "03:00PM-05:00PM"
            ],
            "available_capacity_dose1": 10,
            "available_capacity_dose2": 10
          },
          {
            "session_id": "f3b54615-b8b3-4957-9984-ce0d29239575",
            "date": "31-05-2021",
            "available_capacity": 20,
            "min_age_limit": 45,
            "vaccine": "COVISHIELD",
            "slots": [
              "09:00AM-11:00AM",
              "11:00AM-01:00PM",
              "01:00PM-03:00PM",
              "03:00PM-05:00PM"
            ],
            "available_capacity_dose1": 10,
            "available_capacity_dose2": 10
          }
        ]
      },
      {
        "center_id": 570750,
        "name": "Innao PHC",
        "address": "Innao",
        "state_name": "Arunachal Pradesh",
        "district_name": "Changlang",
        "block_name": "Diyun",
        "pincode": 792103,
        "lat": 27,
        "long": 96,
        "from": "09:00:00",
        "to": "17:00:00",
        "fee_type": "Free",
        "sessions": [
          {
            "session_id": "e3300656-2e3f-4410-b498-c8ba66f0c435",
            "date": "26-05-2021",
            "available_capacity": 20,
            "min_age_limit": 45,
            "vaccine": "COVISHIELD",
            "slots": [
              "09:00AM-11:00AM",
              "11:00AM-01:00PM",
              "01:00PM-03:00PM",
              "03:00PM-05:00PM"
            ],
            "available_capacity_dose1": 10,
            "available_capacity_dose2": 10
          },
          {
            "session_id": "03c93c2f-e659-4fe9-af4f-b6cd0bc403e6",
            "date": "27-05-2021",
            "available_capacity": 20,
            "min_age_limit": 45,
            "vaccine": "COVISHIELD",
            "slots": [
              "09:00AM-11:00AM",
              "11:00AM-01:00PM",
              "01:00PM-03:00PM",
              "03:00PM-05:00PM"
            ],
            "available_capacity_dose1": 10,
            "available_capacity_dose2": 10
          },
          {
            "session_id": "85b55c49-f5db-4dba-bde9-a6a1a0c174c8",
            "date": "28-05-2021",
            "available_capacity": 20,
            "min_age_limit": 45,
            "vaccine": "COVISHIELD",
            "slots": [
              "09:00AM-11:00AM",
              "11:00AM-01:00PM",
              "01:00PM-03:00PM",
              "03:00PM-05:00PM"
            ],
            "available_capacity_dose1": 10,
            "available_capacity_dose2": 10
          },
          {
            "session_id": "f889a79d-4295-4d82-ac48-a793ff285fd7",
            "date": "29-05-2021",
            "available_capacity": 20,
            "min_age_limit": 45,
            "vaccine": "COVISHIELD",
            "slots": [
              "09:00AM-11:00AM",
              "11:00AM-01:00PM",
              "01:00PM-03:00PM",
              "03:00PM-05:00PM"
            ],
            "available_capacity_dose1": 10,
            "available_capacity_dose2": 10
          },
          {
            "session_id": "ecbf506a-7cc8-4e74-9816-cd622ad5293f",
            "date": "30-05-2021",
            "available_capacity": 20,
            "min_age_limit": 45,
            "vaccine": "COVISHIELD",
            "slots": [
              "09:00AM-11:00AM",
              "11:00AM-01:00PM",
              "01:00PM-03:00PM",
              "03:00PM-05:00PM"
            ],
            "available_capacity_dose1": 10,
            "available_capacity_dose2": 10
          },
          {
            "session_id": "c5090df5-e639-4118-920a-b393e9d0504b",
            "date": "31-05-2021",
            "available_capacity": 20,
            "min_age_limit": 45,
            "vaccine": "COVISHIELD",
            "slots": [
              "09:00AM-11:00AM",
              "11:00AM-01:00PM",
              "01:00PM-03:00PM",
              "03:00PM-05:00PM"
            ],
            "available_capacity_dose1": 10,
            "available_capacity_dose2": 10
          }
        ]
      },
      {
        "center_id": 570551,
        "name": "Kharsang PHC",
        "address": "Kharsang",
        "state_name": "Arunachal Pradesh",
        "district_name": "Changlang",
        "block_name": "Khagam Miao",
        "pincode": 792122,
        "lat": 27,
        "long": 96,
        "from": "09:00:00",
        "to": "17:00:00",
        "fee_type": "Free",
        "sessions": [
          {
            "session_id": "e130b095-4e55-4fd7-acc8-6d4d8bfcd5de",
            "date": "26-05-2021",
            "available_capacity": 99,
            "min_age_limit": 45,
            "vaccine": "COVISHIELD",
            "slots": [
              "09:00AM-11:00AM",
              "11:00AM-01:00PM",
              "01:00PM-03:00PM",
              "03:00PM-05:00PM"
            ],
            "available_capacity_dose1": 49,
            "available_capacity_dose2": 50
          },
          {
            "session_id": "bc8a9f54-4d92-405a-aad3-00d740575eb3",
            "date": "27-05-2021",
            "available_capacity": 100,
            "min_age_limit": 45,
            "vaccine": "COVISHIELD",
            "slots": [
              "09:00AM-11:00AM",
              "11:00AM-01:00PM",
              "01:00PM-03:00PM",
              "03:00PM-05:00PM"
            ],
            "available_capacity_dose1": 50,
            "available_capacity_dose2": 50
          },
          {
            "session_id": "66370d85-8b65-49ea-bd9a-6651e4cefcbe",
            "date": "28-05-2021",
            "available_capacity": 100,
            "min_age_limit": 45,
            "vaccine": "COVISHIELD",
            "slots": [
              "09:00AM-11:00AM",
              "11:00AM-01:00PM",
              "01:00PM-03:00PM",
              "03:00PM-05:00PM"
            ],
            "available_capacity_dose1": 50,
            "available_capacity_dose2": 50
          },
          {
            "session_id": "692934f6-d907-401e-bd37-93c936b798c5",
            "date": "29-05-2021",
            "available_capacity": 100,
            "min_age_limit": 45,
            "vaccine": "COVISHIELD",
            "slots": [
              "09:00AM-11:00AM",
              "11:00AM-01:00PM",
              "01:00PM-03:00PM",
              "03:00PM-05:00PM"
            ],
            "available_capacity_dose1": 50,
            "available_capacity_dose2": 50
          },
          {
            "session_id": "d807ae76-1b05-4965-894a-e6da0af59bfe",
            "date": "30-05-2021",
            "available_capacity": 100,
            "min_age_limit": 45,
            "vaccine": "COVISHIELD",
            "slots": [
              "09:00AM-11:00AM",
              "11:00AM-01:00PM",
              "01:00PM-03:00PM",
              "03:00PM-05:00PM"
            ],
            "available_capacity_dose1": 50,
            "available_capacity_dose2": 50
          },
          {
            "session_id": "21cb4b76-1cfa-49fb-897a-8928f7dd2abf",
            "date": "31-05-2021",
            "available_capacity": 100,
            "min_age_limit": 45,
            "vaccine": "COVISHIELD",
            "slots": [
              "09:00AM-11:00AM",
              "11:00AM-01:00PM",
              "01:00PM-03:00PM",
              "03:00PM-05:00PM"
            ],
            "available_capacity_dose1": 50,
            "available_capacity_dose2": 50
          }
        ]
      },
      {
        "center_id": 565716,
        "name": "CHC Jairampur",
        "address": "Jairampur",
        "state_name": "Arunachal Pradesh",
        "district_name": "Changlang",
        "block_name": "Jairampur",
        "pincode": 792121,
        "lat": 27,
        "long": 96,
        "from": "09:00:00",
        "to": "17:00:00",
        "fee_type": "Free",
        "sessions": [
          {
            "session_id": "69e8f266-a688-4359-912d-8dc747d166b8",
            "date": "26-05-2021",
            "available_capacity": 20,
            "min_age_limit": 45,
            "vaccine": "COVISHIELD",
            "slots": [
              "09:00AM-11:00AM",
              "11:00AM-01:00PM",
              "01:00PM-03:00PM",
              "03:00PM-05:00PM"
            ],
            "available_capacity_dose1": 10,
            "available_capacity_dose2": 10
          },
          {
            "session_id": "717a2694-7618-4684-8d27-44f0d5b95ce2",
            "date": "27-05-2021",
            "available_capacity": 19,
            "min_age_limit": 45,
            "vaccine": "COVISHIELD",
            "slots": [
              "09:00AM-11:00AM",
              "11:00AM-01:00PM",
              "01:00PM-03:00PM",
              "03:00PM-05:00PM"
            ],
            "available_capacity_dose1": 9,
            "available_capacity_dose2": 10
          },
          {
            "session_id": "d0163c4e-5cc4-4753-bbf7-4adc3ca10539",
            "date": "28-05-2021",
            "available_capacity": 19,
            "min_age_limit": 45,
            "vaccine": "COVISHIELD",
            "slots": [
              "09:00AM-11:00AM",
              "11:00AM-01:00PM",
              "01:00PM-03:00PM",
              "03:00PM-05:00PM"
            ],
            "available_capacity_dose1": 9,
            "available_capacity_dose2": 10
          },
          {
            "session_id": "94038d72-876a-46cc-9636-f1a59d8750c3",
            "date": "29-05-2021",
            "available_capacity": 20,
            "min_age_limit": 45,
            "vaccine": "COVISHIELD",
            "slots": [
              "09:00AM-11:00AM",
              "11:00AM-01:00PM",
              "01:00PM-03:00PM",
              "03:00PM-05:00PM"
            ],
            "available_capacity_dose1": 10,
            "available_capacity_dose2": 10
          },
          {
            "session_id": "f3c05d90-e4d7-438b-a6a8-0eaba91079f0",
            "date": "30-05-2021",
            "available_capacity": 20,
            "min_age_limit": 45,
            "vaccine": "COVISHIELD",
            "slots": [
              "09:00AM-11:00AM",
              "11:00AM-01:00PM",
              "01:00PM-03:00PM",
              "03:00PM-05:00PM"
            ],
            "available_capacity_dose1": 10,
            "available_capacity_dose2": 10
          },
          {
            "session_id": "a5d5a134-2a40-452b-b73b-4548f266ce0e",
            "date": "31-05-2021",
            "available_capacity": 20,
            "min_age_limit": 45,
            "vaccine": "COVISHIELD",
            "slots": [
              "09:00AM-11:00AM",
              "11:00AM-01:00PM",
              "01:00PM-03:00PM",
              "03:00PM-05:00PM"
            ],
            "available_capacity_dose1": 10,
            "available_capacity_dose2": 10
          }
        ]
      },
      {
        "center_id": 571709,
        "name": "Khimiyong PHC",
        "address": "Khimiyong",
        "state_name": "Arunachal Pradesh",
        "district_name": "Changlang",
        "block_name": "Changlang",
        "pincode": 792120,
        "lat": 26,
        "long": 95,
        "from": "09:00:00",
        "to": "17:00:00",
        "fee_type": "Free",
        "sessions": [
          {
            "session_id": "ec6590a9-b024-48e3-aaad-95bb3a23643e",
            "date": "26-05-2021",
            "available_capacity": 0,
            "min_age_limit": 45,
            "vaccine": "COVISHIELD",
            "slots": [
              "09:00AM-11:00AM",
              "11:00AM-01:00PM",
              "01:00PM-03:00PM",
              "03:00PM-05:00PM"
            ],
            "available_capacity_dose1": 0,
            "available_capacity_dose2": 0
          },
          {
            "session_id": "fd421f39-8584-4af4-81ce-a709c695d3b4",
            "date": "27-05-2021",
            "available_capacity": 0,
            "min_age_limit": 45,
            "vaccine": "COVISHIELD",
            "slots": [
              "09:00AM-11:00AM",
              "11:00AM-01:00PM",
              "01:00PM-03:00PM",
              "03:00PM-05:00PM"
            ],
            "available_capacity_dose1": 0,
            "available_capacity_dose2": 0
          },
          {
            "session_id": "618c8346-cd14-4367-8a55-4a07f5dcc11f",
            "date": "28-05-2021",
            "available_capacity": 0,
            "min_age_limit": 45,
            "vaccine": "COVISHIELD",
            "slots": [
              "09:00AM-11:00AM",
              "11:00AM-01:00PM",
              "01:00PM-03:00PM",
              "03:00PM-05:00PM"
            ],
            "available_capacity_dose1": 0,
            "available_capacity_dose2": 0
          },
          {
            "session_id": "d26f58b8-e7bc-4b5c-a938-837a1c6e7c65",
            "date": "29-05-2021",
            "available_capacity": 0,
            "min_age_limit": 45,
            "vaccine": "COVISHIELD",
            "slots": [
              "09:00AM-11:00AM",
              "11:00AM-01:00PM",
              "01:00PM-03:00PM",
              "03:00PM-05:00PM"
            ],
            "available_capacity_dose1": 0,
            "available_capacity_dose2": 0
          },
          {
            "session_id": "d8788381-6e95-43b9-8220-34b3fcb15a72",
            "date": "30-05-2021",
            "available_capacity": 0,
            "min_age_limit": 45,
            "vaccine": "COVISHIELD",
            "slots": [
              "09:00AM-11:00AM",
              "11:00AM-01:00PM",
              "01:00PM-03:00PM",
              "03:00PM-05:00PM"
            ],
            "available_capacity_dose1": 0,
            "available_capacity_dose2": 0
          },
          {
            "session_id": "bd1b3a2e-2068-445e-80d4-6b4773a11c6c",
            "date": "31-05-2021",
            "available_capacity": 0,
            "min_age_limit": 45,
            "vaccine": "COVISHIELD",
            "slots": [
              "09:00AM-11:00AM",
              "11:00AM-01:00PM",
              "01:00PM-03:00PM",
              "03:00PM-05:00PM"
            ],
            "available_capacity_dose1": 0,
            "available_capacity_dose2": 0
          }
        ]
      },
      {
        "center_id": 566294,
        "name": "CHC Bordumsa",
        "address": "Bordumsa",
        "state_name": "Arunachal Pradesh",
        "district_name": "Changlang",
        "block_name": "Bordumsa",
        "pincode": 792056,
        "lat": 27,
        "long": 95,
        "from": "09:00:00",
        "to": "17:00:00",
        "fee_type": "Free",
        "sessions": [
          {
            "session_id": "6ff8a075-38c3-4c65-b36e-4c551aceb0ec",
            "date": "26-05-2021",
            "available_capacity": 0,
            "min_age_limit": 45,
            "vaccine": "COVISHIELD",
            "slots": [
              "09:00AM-11:00AM",
              "11:00AM-01:00PM",
              "01:00PM-03:00PM",
              "03:00PM-05:00PM"
            ],
            "available_capacity_dose1": 0,
            "available_capacity_dose2": 0
          },
          {
            "session_id": "df32145e-1292-47a6-912d-3e07b5eb9d21",
            "date": "27-05-2021",
            "available_capacity": 0,
            "min_age_limit": 45,
            "vaccine": "COVISHIELD",
            "slots": [
              "09:00AM-11:00AM",
              "11:00AM-01:00PM",
              "01:00PM-03:00PM",
              "03:00PM-05:00PM"
            ],
            "available_capacity_dose1": 0,
            "available_capacity_dose2": 0
          },
          {
            "session_id": "025cf2f4-7fa7-4d18-8dea-76d64910b235",
            "date": "28-05-2021",
            "available_capacity": 0,
            "min_age_limit": 45,
            "vaccine": "COVISHIELD",
            "slots": [
              "09:00AM-11:00AM",
              "11:00AM-01:00PM",
              "01:00PM-03:00PM",
              "03:00PM-05:00PM"
            ],
            "available_capacity_dose1": 0,
            "available_capacity_dose2": 0
          },
          {
            "session_id": "c58a7dbb-128b-4f34-a2dc-58f5a6ba5ea4",
            "date": "29-05-2021",
            "available_capacity": 0,
            "min_age_limit": 45,
            "vaccine": "COVISHIELD",
            "slots": [
              "09:00AM-11:00AM",
              "11:00AM-01:00PM",
              "01:00PM-03:00PM",
              "03:00PM-06:00PM"
            ],
            "available_capacity_dose1": 0,
            "available_capacity_dose2": 0
          },
          {
            "session_id": "939dddec-ee31-40b3-9fb5-01f9478bd78a",
            "date": "30-05-2021",
            "available_capacity": 0,
            "min_age_limit": 45,
            "vaccine": "COVISHIELD",
            "slots": [
              "09:00AM-11:00AM",
              "11:00AM-01:00PM",
              "01:00PM-03:00PM",
              "03:00PM-05:00PM"
            ],
            "available_capacity_dose1": 0,
            "available_capacity_dose2": 0
          },
          {
            "session_id": "b46a5122-1dd6-40d8-be43-7275d10ebd01",
            "date": "31-05-2021",
            "available_capacity": 0,
            "min_age_limit": 45,
            "vaccine": "COVISHIELD",
            "slots": [
              "09:00AM-11:00AM",
              "11:00AM-01:00PM",
              "01:00PM-03:00PM",
              "03:00PM-05:00PM"
            ],
            "available_capacity_dose1": 0,
            "available_capacity_dose2": 0
          }
        ]
      },
      {
        "center_id": 105352,
        "name": "Diyun CHC",
        "address": "Diyun",
        "state_name": "Arunachal Pradesh",
        "district_name": "Changlang",
        "block_name": "Diyun",
        "pincode": 792103,
        "lat": 27,
        "long": 96,
        "from": "09:00:00",
        "to": "17:00:00",
        "fee_type": "Free",
        "sessions": [
          {
            "session_id": "254ca67e-56e8-4de8-9fc2-d426a3506cf7",
            "date": "26-05-2021",
            "available_capacity": 20,
            "min_age_limit": 45,
            "vaccine": "COVISHIELD",
            "slots": [
              "09:00AM-11:00AM",
              "11:00AM-01:00PM",
              "01:00PM-03:00PM",
              "03:00PM-05:00PM"
            ],
            "available_capacity_dose1": 10,
            "available_capacity_dose2": 10
          },
          {
            "session_id": "638739b9-5faa-4e18-b0c2-f1f05fa5ba9e",
            "date": "27-05-2021",
            "available_capacity": 20,
            "min_age_limit": 45,
            "vaccine": "COVISHIELD",
            "slots": [
              "09:00AM-11:00AM",
              "11:00AM-01:00PM",
              "01:00PM-03:00PM",
              "03:00PM-05:00PM"
            ],
            "available_capacity_dose1": 10,
            "available_capacity_dose2": 10
          },
          {
            "session_id": "9defb61c-5c46-4a2a-809d-e25144524cb8",
            "date": "28-05-2021",
            "available_capacity": 20,
            "min_age_limit": 45,
            "vaccine": "COVISHIELD",
            "slots": [
              "09:00AM-11:00AM",
              "11:00AM-01:00PM",
              "01:00PM-03:00PM",
              "03:00PM-05:00PM"
            ],
            "available_capacity_dose1": 10,
            "available_capacity_dose2": 10
          },
          {
            "session_id": "2e62ee0e-054b-43f2-b6cd-7d451873ca60",
            "date": "29-05-2021",
            "available_capacity": 20,
            "min_age_limit": 45,
            "vaccine": "COVISHIELD",
            "slots": [
              "09:00AM-11:00AM",
              "11:00AM-01:00PM",
              "01:00PM-03:00PM",
              "03:00PM-05:00PM"
            ],
            "available_capacity_dose1": 10,
            "available_capacity_dose2": 10
          },
          {
            "session_id": "2b207542-c59f-4684-b11c-b86598afb7f5",
            "date": "30-05-2021",
            "available_capacity": 20,
            "min_age_limit": 45,
            "vaccine": "COVISHIELD",
            "slots": [
              "09:00AM-11:00AM",
              "11:00AM-01:00PM",
              "01:00PM-03:00PM",
              "03:00PM-05:00PM"
            ],
            "available_capacity_dose1": 10,
            "available_capacity_dose2": 10
          },
          {
            "session_id": "052b0043-33cb-4e7a-869b-ecc46af52d34",
            "date": "31-05-2021",
            "available_capacity": 20,
            "min_age_limit": 45,
            "vaccine": "COVISHIELD",
            "slots": [
              "09:00AM-11:00AM",
              "11:00AM-01:00PM",
              "01:00PM-03:00PM",
              "03:00PM-05:00PM"
            ],
            "available_capacity_dose1": 10,
            "available_capacity_dose2": 10
          }
        ]
      }
    ]
  }